setup.py
dm/__init__.py
dm.zope.generate.egg-info/PKG-INFO
dm.zope.generate.egg-info/SOURCES.txt
dm.zope.generate.egg-info/dependency_links.txt
dm.zope.generate.egg-info/namespace_packages.txt
dm.zope.generate.egg-info/not-zip-safe
dm.zope.generate.egg-info/requires.txt
dm.zope.generate.egg-info/top_level.txt
dm/zope/__init__.py
dm/zope/generate/LICENSE.txt
dm/zope/generate/README.txt
dm/zope/generate/VERSION.txt
dm/zope/generate/__init__.py
dm/zope/generate/constructor.py
dm/zope/generate/generic_add_form-4.zpt
dm/zope/generate/generic_add_form.zpt
dm/zope/generate/test/__init__.py
dm/zope/generate/test/configure.zcml
dm/zope/generate/tests/__init__.py
dm/zope/generate/tests/test_constructor.py