Metadata-Version: 1.1
Name: dm.zope.generate
Version: 1.1.1
Summary: Code generation to facilitate Zope[2] application development.
Home-page: http://pypi.python.org/pypi/dm.zope.generate
Author: Dieter Maurer
Author-email: dieter@handshake.de
License: ZPL
Keywords: application development zope
Platform: UNKNOWN
Classifier: Development Status :: 5 - Production/Stable
Classifier: Intended Audience :: Developers
Classifier: License :: OSI Approved :: Zope Public License
Classifier: Framework :: Zope2
Classifier: Framework :: Zope
Classifier: Framework :: Zope :: 4
Classifier: Operating System :: OS Independent
Classifier: Programming Language :: Python
Classifier: Programming Language :: Python :: 2.7
Classifier: Programming Language :: Python :: 3
Classifier: Topic :: Utilities
